<OpenSearchDescription xmlns="http://a9.com/-/spec/opensearch/1.1/" xmlns:moz="http://www.mozilla.org/2006/browser/search/">
<ShortName>aisec</ShortName>
<Description>ai search</Description>
<InputEncoding>UTF-8</InputEncoding>
<Image width="16" height="16" type="image/x-icon">https://www.perplexity.ai/static/icons/favicon.ico</Image>
<Url type="text/html" method="get" template="https://aise.pages.dev?q={searchTerms}"/>
<moz:SearchForm>https://aisec.playcode.io/</moz:SearchForm>
</OpenSearchDescription>